README.md
setup.cfg
setup.py
RangeDisplay/RangeDisplay.py
RangeDisplay/__init__.py
RangeDisplay.egg-info/PKG-INFO
RangeDisplay.egg-info/SOURCES.txt
RangeDisplay.egg-info/dependency_links.txt
RangeDisplay.egg-info/top_level.txt