Metadata-Version: 2.1
Name: RangeDisplay
Version: 2021.7
Summary: 2D Fractional display widget for Python Tkinter GUI developement
Home-page: https://github.com/harshvinay752/RangeDisplay
Author: Harsh Agarwal
Author-email: harshvinay752@gmail.com
License: MIT
Download-URL: https://github.com/harshvinay752/RangeDisplay/archive/refs/tags/2021.7.tar.gz
Keywords: Python,tkinter,range,display,widget
Platform: UNKNOWN
Classifier: Development Status :: 3 - Alpha
Classifier: Intended Audience :: Developers
Classifier: Topic :: Software Development :: Build Tools
Classifier: License :: OSI Approved :: MIT License
Classifier: Programming Language :: Python :: 3
Classifier: Programming Language :: Python :: 3.4
Classifier: Programming Language :: Python :: 3.5
Classifier: Programming Language :: Python :: 3.6
